binance_mcp_server/__init__.py
binance_mcp_server/cli.py
binance_mcp_server/config.py
binance_mcp_server/security.py
binance_mcp_server/server.py
binance_mcp_server/utils.py
binance_mcp_server/tools/__init__.py
binance_mcp_server/tools/create_order.py
binance_mcp_server/tools/get_account_snapshot.py
binance_mcp_server/tools/get_available_assets.py
binance_mcp_server/tools/get_balance.py
binance_mcp_server/tools/get_deposit_address.py
binance_mcp_server/tools/get_deposit_history.py
binance_mcp_server/tools/get_fee_info.py
binance_mcp_server/tools/get_liquidation_history.py
binance_mcp_server/tools/get_order_book.py
binance_mcp_server/tools/get_orders.py
binance_mcp_server/tools/get_pnl.py
binance_mcp_server/tools/get_position_info.py
binance_mcp_server/tools/get_ticker.py
binance_mcp_server/tools/get_ticker_price.py
binance_mcp_server/tools/get_universal_transfer_history.py
binance_mcp_server/tools/get_withdraw_history.py
binance_mcp_server-1.2.7.dist-info/licenses/LICENSE
binance_mcp_server-1.2.7.dist-info/METADATA
binance_mcp_server-1.2.7.dist-info/WHEEL
binance_mcp_server-1.2.7.dist-info/entry_points.txt
binance_mcp_server-1.2.7.dist-info/top_level.txt
binance_mcp_server-1.2.7.dist-info/RECORD
