Metadata-Version: 2.4
Name: binance-mcp-server
Version: 1.2.7
Summary: Binance's Model Context Protocol (MCP). Designed to support developers building crypto trading AI Agents.
Author-email: "AnalyticAce (DOSSEH Shalom)" <dossehdosseh14@gmail.com>
Project-URL: Homepage, https://analyticace.github.io/BinanceMCPServer/
Keywords: binance,mcp,server,fastmcp,crypto,trading,finance
Classifier: Programming Language :: Python :: 3
Classifier: License :: OSI Approved :: MIT License
Classifier: Operating System :: OS Independent
Classifier: Intended Audience :: Developers
Requires-Python: >=3.10
License-File: LICENSE
Requires-Dist: fastmcp>=2.5.1
Requires-Dist: python-binance>=1.0.29
Requires-Dist: typer>=0.16.0
Dynamic: license-file
